AsyncFIFO/design/fifo_mem.sv
`ifndef FIFO_MEM_SV
`define FIFO_MEM_SV

module fifo_mem #(parameter data_width =  8, ptr_width =  9, depth = 256)( wclk,rclk,r_rst_n,w_rst_n,w_en,r_en,full,empty, data_in,  waddr,raddr,  data_out);

input bit wclk,rclk,r_rst_n,w_rst_n,w_en,r_en,full,empty;
input logic [ptr_width-1:0]  waddr, raddr;

input logic [data_width-1:0] data_in;
output logic [data_width-1:0]data_out;

logic [data_width-1:0] fifo [0: depth-1];

  always_ff@(posedge wclk)
begin
  if(w_en & !full & w_rst_n)
begin
fifo[waddr[ptr_width-1:0]]<=data_in; // WRITE OPERATION
end
end
assign data_out=fifo[raddr[ptr_width-1:0]]; // READ OPERATION
endmodule
`endif

AsyncFIFO/design/read_ptr.sv
`ifndef READ_PTR_SV
`define READ_PTR_SV

module read_ptr #(parameter ptr_width=8)( rclk, r_rst_n, r_en,   wptr_sync,  raddr, rptr,  empty);

input bit rclk,r_rst_n, r_en;
input logic [ptr_width:0]  wptr_sync;
output bit empty;
output logic [ptr_width:0] raddr, rptr;

 logic rempty;
 logic emptyr;
 logic readempty;

logic [ptr_width:0]raddr_next;
logic [ptr_width:0]rptr_next;


assign raddr_next= raddr + (r_en & !empty);
assign rptr_next=(raddr_next>>1)^raddr_next; // GRAY CONVERTED VALUE
assign rempty= (wptr_sync == rptr_next); // CHECKING THE EMPTY CONDITION 

always_ff@(posedge rclk or negedge r_rst_n)
begin
	if(!r_rst_n)
		begin
		raddr<=0; //default value
		rptr<=0;
		end 
	else begin
		raddr<=raddr_next;//incrementing binary read pointer
		rptr<=rptr_next;//incrementing gray read pointer
	end
end

always_ff@(posedge rclk or negedge r_rst_n)
begin
if(!r_rst_n)
	empty<=1;//initial empty condition
else
	empty<=rempty;
	
end

endmodule
`endif

AsyncFIFO/design/write_ptr.sv
`ifndef WRITE_PTR_SV
`define WRITE_PTR_SV

module write_ptr #(parameter ptr_width=9)(wclk, w_rst_n, w_en,  rptr_sync,  waddr, wptr, full);

input bit wclk, w_rst_n, w_en;
input logic [ptr_width-1:0] rptr_sync;

output bit full;
output logic [ptr_width-1:0] waddr, wptr;

logic wfull;
logic [ptr_width-1:0]waddr_next; 
logic [ptr_width-1:0]wptr_next;

assign waddr_next= waddr + (w_en & !full);
assign wptr_next= (waddr_next>>1)^waddr_next; 

always_ff@(posedge wclk or negedge w_rst_n)
begin
	if(!w_rst_n)
		begin
		waddr<='0; //set default value
		wptr<='0;
		end 
	else begin
		waddr<=waddr_next;//incrementing binary write pointer
		wptr<=wptr_next;//incrementing gray write pointer
	end
end

always_ff@(posedge wclk or negedge w_rst_n)
begin
if(!w_rst_n)
	full<=0;
else
	full<=wfull;
end
assign wfull= (wptr_next=={~rptr_sync[ptr_width:ptr_width-1],rptr_sync[ptr_width-2:0]});// FULL CONDITION
	
endmodule
  `endif

AsyncFIFO/design/r2wsync.sv
`ifndef R2WSYNC_SV
`define R2WSYNC_SV
module r2wsync #(parameter ptr_width=9)( wclk, w_rst_n, rptr,  rptr_sync);

input bit wclk, w_rst_n;
input logic [ptr_width-1:0]  rptr;
output logic [ptr_width-1:0]rptr_sync;

logic [ptr_width:0] q1;
  always_ff@(posedge wclk) begin
    if(!w_rst_n) begin
      q1 <= 0;
      rptr_sync <= 0;
    end
    else begin
      q1 <= rptr;
      rptr_sync <= q1;
    end
  end
endmodule

`endif

AsyncFIFO/design/w2rsync.sv
`ifndef W2RSYNC_SV
`define W2RSYNC_SV
module w2rsync #(parameter  ptr_width=9)( rclk, r_rst_n,  wptr ,  wptr_sync);

input bit rclk,r_rst_n;
input [ptr_width-1:0] wptr;
output logic [ptr_width-1:0]  wptr_sync;

 logic [ptr_width:0] q2;
  always_ff@(posedge rclk) begin
    if(!r_rst_n) begin
      q2 <= 0;
      wptr_sync <= 0;//one cycle delay
    end
    else begin
      q2 <= wptr;
      wptr_sync <= q2;//two cycle delay
    end
  end
endmodule
`endif

AsyncFIFO/design/top.sv
// Code your design here
// Synchronizers
`include "../design/w2rsync.sv"
`include "../design/r2wsync.sv"

// Pointer handlers
`include "../design/write_ptr.sv"
`include "../design/read_ptr.sv"

// Memory
`include "../design/fifo_mem.sv"

module top #(parameter depth=409, data_width=8, ptr_width=9) (
    input  logic                  wclk,
    input  logic                  w_rst_n,
    input  logic                  rclk,
    input  logic                  r_rst_n,
    input  logic                  w_en,
    input  logic                  r_en,
    input  logic [data_width-1:0] data_in,
    output logic [data_width-1:0] data_out,
    output logic                  full,
    output logic                  empty
);

    // Internal signals
    logic [ptr_width-1:0] wptr;
    logic [ptr_width-1:0] rptr;
    logic [ptr_width-1:0] wptr_sync;
    logic [ptr_width-1:0] rptr_sync;
    logic [ptr_width-1:0] waddr;
    logic [ptr_width-1:0] raddr;

    // 2-flop synchronizers
    w2rsync #(ptr_width) w2rsync_inst (
        .rclk     (rclk),
        .r_rst_n  (r_rst_n),
        .wptr     (wptr),
        .wptr_sync(wptr_sync)
    );

    r2wsync #(ptr_width) r2wsync_inst (
        .wclk     (wclk),
        .w_rst_n  (w_rst_n),
        .rptr     (rptr),
        .rptr_sync(rptr_sync)
    );

    // Write pointer handler
    write_ptr #(ptr_width) write_ptr_inst (
        .wclk      (wclk),
        .w_rst_n   (w_rst_n),
        .w_en      (w_en),
        .rptr_sync (rptr_sync),
        .waddr     (waddr),
        .wptr      (wptr),
        .full      (full)
    );

    // Read pointer handler
    read_ptr #(ptr_width) read_ptr_inst (
        .rclk      (rclk),
        .r_rst_n   (r_rst_n),
        .r_en      (r_en),
        .wptr_sync (wptr_sync),
        .raddr     (raddr),
        .rptr      (rptr),
        .empty     (empty)
    );

    // FIFO memory
    fifo_mem #(data_width, ptr_width, depth) fifo_mem_inst (
        .wclk    (wclk),
        .rclk    (rclk),
        .r_rst_n (r_rst_n),
        .w_rst_n (w_rst_n),
        .w_en    (w_en),
        .r_en    (r_en),
        .full    (full),
        .empty   (empty),
        .data_in (data_in),
        .waddr   (waddr),
        .raddr   (raddr),
        .data_out(data_out)
    );

    // Dump waves
    initial begin
        $dumpfile("dump.vcd");
        $dumpvars(0, top);
    end

endmodule

AsyncFIFO/tb/dump.vcd
$date
	Thu Jul  2 12:24:25 2026
$end
$version
	Icarus Verilog
$end
$timescale
	1ps
$end
$scope module top $end
$var wire 8 ! data_in [7:0] $end
$var wire 1 " r_en $end
$var wire 1 # r_rst_n $end
$var wire 1 $ rclk $end
$var wire 1 % w_en $end
$var wire 1 & w_rst_n $end
$var wire 1 ' wclk $end
$var wire 9 ( wptr_sync [8:0] $end
$var wire 9 ) wptr [8:0] $end
$var wire 9 * waddr [8:0] $end
$var wire 9 + rptr_sync [8:0] $end
$var wire 9 , rptr [8:0] $end
$var wire 9 - raddr [8:0] $end
$var wire 1 . full $end
$var wire 1 / empty $end
$var wire 8 0 data_out [7:0] $end
$var parameter 32 1 data_width $end
$var parameter 32 2 depth $end
$var parameter 32 3 ptr_width $end
$scope module fifo_mem_inst $end
$var wire 8 4 data_in [7:0] $end
$var wire 8 5 data_out [7:0] $end
$var wire 1 6 empty $end
$var wire 1 7 full $end
$var wire 1 8 r_en $end
$var wire 1 9 r_rst_n $end
$var wire 1 : rclk $end
$var wire 1 ; w_en $end
$var wire 1 < w_rst_n $end
$var wire 1 = wclk $end
$var wire 9 > waddr [8:0] $end
$var wire 9 ? raddr [8:0] $end
$var parameter 32 @ data_width $end
$var parameter 32 A depth $end
$var parameter 32 B ptr_width $end
$upscope $end
$scope module r2wsync_inst $end
$var wire 1 C w_rst_n $end
$var wire 1 D wclk $end
$var wire 9 E rptr [8:0] $end
$var parameter 32 F ptr_width $end
$var reg 10 G q1 [9:0] $end
$var reg 9 H rptr_sync [8:0] $end
$upscope $end
$scope module read_ptr_inst $end
$var wire 1 I r_en $end
$var wire 1 J r_rst_n $end
$var wire 1 K rclk $end
$var wire 9 L rptr_next [8:0] $end
$var wire 9 M wptr_sync [8:0] $end
$var wire 1 N rempty $end
$var wire 9 O raddr_next [8:0] $end
$var parameter 32 P ptr_width $end
$var reg 9 Q raddr [8:0] $end
$var reg 9 R rptr [8:0] $end
$var reg 1 / empty $end
$upscope $end
$scope module w2rsync_inst $end
$var wire 1 S r_rst_n $end
$var wire 1 T rclk $end
$var wire 9 U wptr [8:0] $end
$var parameter 32 V ptr_width $end
$var reg 10 W q2 [9:0] $end
$var reg 9 X wptr_sync [8:0] $end
$upscope $end
$scope module write_ptr_inst $end
$var wire 9 Y rptr_sync [8:0] $end
$var wire 1 Z w_en $end
$var wire 1 [ w_rst_n $end
$var wire 1 \ wclk $end
$var wire 9 ] wptr_next [8:0] $end
$var wire 1 ^ wfull $end
$var wire 9 _ waddr_next [8:0] $end
$var parameter 32 ` ptr_width $end
$var reg 9 a waddr [8:0] $end
$var reg 9 b wptr [8:0] $end
$var reg 1 . full $end
$upscope $end
$upscope $end
$enddefinitions $end
$comment Show the parameter values. $end
$dumpall
b1001 `
b1001 V
b1001 P
b1001 F
b1001 B
b110011001 A
b1000 @
b1001 3
b110011001 2
b1000 1
$end
#0
$dumpvars
b0 b
b0 a
b0 _
0^
b0 ]
1\
0[
0Z
b0 Y
b0 X
b0 W
b0 U
1T
0S
b0 R
b0 Q
b0 O
1N
b0 M
b0 L
1K
0J
0I
b0 H
b0 G
b0 E
1D
0C
b0 ?
b0 >
1=
0<
0;
1:
09
08
07
16
bx 5
b0 4
bx 0
1/
0.
b0 -
b0 ,
b0 +
b0 *
b0 )
b0 (
1'
0&
0%
1$
0#
0"
b0 !
$end
#4000
0D
0\
0=
0'
#8000
1D
1\
1=
1'
#10000
0T
0K
0:
0$
#12000
0D
0\
0=
0'
#16000
1D
1\
1=
1'
#20000
0D
0\
0=
0'
1T
1K
1:
1$
#24000
1D
1\
1=
1'
#28000
0D
0\
0=
0'
#30000
0T
0K
0:
0$
#32000
1S
1J
19
1#
1C
1[
1<
1&
1D
1\
1=
1'
#36000
0D
0\
0=
0'
#40000
1D
1\
1=
1'
1T
1K
1:
1$
#44000
0D
0\
0=
0'
#48000
1D
1\
1=
1'
#50000
0T
0K
0:
0$
#52000
0D
0\
0=
0'
#56000
b1 ]
b1 _
b1111101 !
b1111101 4
1Z
1;
1%
1D
1\
1=
1'
#60000
0D
0\
0=
0'
1T
1K
1:
1$
#64000
0Z
0;
0%
b1 ]
b1 )
b1 U
b1 b
b1 _
b1 *
b1 >
b1 a
b1111101 0
b1111101 5
1D
1\
1=
1'
#68000
0D
0\
0=
0'
#70000
0T
0K
0:
0$
#72000
b11 ]
b10 _
b1110100 !
b1110100 4
1Z
1;
1%
1D
1\
1=
1'
#76000
0D
0\
0=
0'
#80000
0Z
0;
0%
b11 ]
b11 )
b11 U
b11 b
b10 _
b10 *
b10 >
b10 a
b1 W
1D
1\
1=
1'
1T
1K
1:
1$
#84000
0D
0\
0=
0'
#88000
b10 ]
b11 _
b10101011 !
b10101011 4
1Z
1;
1%
1D
1\
1=
1'
#90000
0T
0K
0:
0$
#92000
0D
0\
0=
0'
#96000
0Z
0;
0%
b10 ]
b10 )
b10 U
b10 b
b11 _
b11 *
b11 >
b11 a
1D
1\
1=
1'
#100000
0N
b1 (
b1 M
b1 X
b10 W
0D
0\
0=
0'
1T
1K
1:
1$
#104000
b110 ]
b100 _
b10100000 !
b10100000 4
1Z
1;
1%
1D
1\
1=
1'
#108000
0D
0\
0=
0'
#110000
0T
0K
0:
0$
#112000
0Z
0;
0%
b110 ]
b110 )
b110 U
b110 b
b100 _
b100 *
b100 >
b100 a
1D
1\
1=
1'
#116000
0D
0\
0=
0'
#120000
b111 ]
b101 _
b10011000 !
b10011000 4
1Z
1;
1%
b10 (
b10 M
b10 X
b110 W
06
0/
1D
1\
1=
1'
1T
1K
1:
1$
#124000
0D
0\
0=
0'
#128000
0Z
0;
0%
b111 ]
b111 )
b111 U
b111 b
b101 _
b101 *
b101 >
b101 a
1D
1\
1=
1'
#130000
0T
0K
0:
0$
#132000
0D
0\
0=
0'
#136000
1D
1\
1=
1'
#140000
b110 (
b110 M
b110 X
b111 W
0D
0\
0=
0'
1T
1K
1:
1$
#144000
1D
1\
1=
1'
#148000
0D
0\
0=
0'
#150000
0T
0K
0:
0$
#152000
1D
1\
1=
1'
#156000
0D
0\
0=
0'
#160000
b0 ]
16
1/
b0 )
b0 U
b0 b
b0 _
b0 *
b0 >
b0 a
0S
0J
09
0#
0C
0[
0<
0&
b111 (
b111 M
b111 X
1D
1\
1=
1'
1T
1K
1:
1$
#164000
0D
0\
0=
0'
#168000
1D
1\
1=
1'
#170000
0T
0K
0:
0$
#172000
0D
0\
0=
0'
#176000
1D
1\
1=
1'
#180000
1N
b0 (
b0 M
b0 X
b0 W
0D
0\
0=
0'
1T
1K
1:
1$
#184000
1D
1\
1=
1'
#188000
0D
0\
0=
0'
#190000
0T
0K
0:
0$
#192000
1D
1\
1=
1'
#192001
1S
1J
19
1#
1C
1[
1<
1&
